WenjianxitongCengcijiegouBiaozhunZhongwenban/README.md
WenjianxitongCengcijiegouBiaozhunZhongwenban/__init__.py
WenjianxitongCengcijiegouBiaozhunZhongwenban/__main__.py
WenjianxitongCengcijiegouBiaozhunZhongwenban/file.epub
WenjianxitongCengcijiegouBiaozhunZhongwenban/index.html
WenjianxitongCengcijiegouBiaozhunZhongwenban/css/__init__.py
WenjianxitongCengcijiegouBiaozhunZhongwenban/css/annotations.css
WenjianxitongCengcijiegouBiaozhunZhongwenban/css/main.css
WenjianxitongCengcijiegouBiaozhunZhongwenban/css/normalize.css
WenjianxitongCengcijiegouBiaozhunZhongwenban/css/popup.css
WenjianxitongCengcijiegouBiaozhunZhongwenban/font/__init__.py
WenjianxitongCengcijiegouBiaozhunZhongwenban/font/fontello.eot
WenjianxitongCengcijiegouBiaozhunZhongwenban/font/fontello.svg
WenjianxitongCengcijiegouBiaozhunZhongwenban/font/fontello.ttf
WenjianxitongCengcijiegouBiaozhunZhongwenban/font/fontello.woff
WenjianxitongCengcijiegouBiaozhunZhongwenban/img/__init__.py
WenjianxitongCengcijiegouBiaozhunZhongwenban/img/annotator-glyph-sprite.png
WenjianxitongCengcijiegouBiaozhunZhongwenban/img/annotator-icon-sprite.png
WenjianxitongCengcijiegouBiaozhunZhongwenban/img/apple-touch-icon.png
WenjianxitongCengcijiegouBiaozhunZhongwenban/img/cancelfullscreen.png
WenjianxitongCengcijiegouBiaozhunZhongwenban/img/close.png
WenjianxitongCengcijiegouBiaozhunZhongwenban/img/fullscreen.png
WenjianxitongCengcijiegouBiaozhunZhongwenban/img/loader.gif
WenjianxitongCengcijiegouBiaozhunZhongwenban/img/menu-icon.png
WenjianxitongCengcijiegouBiaozhunZhongwenban/img/save.png
WenjianxitongCengcijiegouBiaozhunZhongwenban/img/saved.png
WenjianxitongCengcijiegouBiaozhunZhongwenban/img/settings-s.png
WenjianxitongCengcijiegouBiaozhunZhongwenban/img/settings.png
WenjianxitongCengcijiegouBiaozhunZhongwenban/img/star.png
WenjianxitongCengcijiegouBiaozhunZhongwenban/js/__init__.py
WenjianxitongCengcijiegouBiaozhunZhongwenban/js/epub.js
WenjianxitongCengcijiegouBiaozhunZhongwenban/js/epub.min.js
wenjianxitong_cengcijiegou_biaozhun_zhongwenban-2024.3.3.0.dist-info/METADATA
wenjianxitong_cengcijiegou_biaozhun_zhongwenban-2024.3.3.0.dist-info/WHEEL
wenjianxitong_cengcijiegou_biaozhun_zhongwenban-2024.3.3.0.dist-info/entry_points.txt
wenjianxitong_cengcijiegou_biaozhun_zhongwenban-2024.3.3.0.dist-info/top_level.txt
wenjianxitong_cengcijiegou_biaozhun_zhongwenban-2024.3.3.0.dist-info/RECORD
